ax_lang/__init__.py
ax_lang/exceptions.py
ax_lang-0.15.0.dist-info/METADATA
ax_lang-0.15.0.dist-info/WHEEL
ax_lang-0.15.0.dist-info/entry_points.txt
ax_lang-0.15.0.dist-info/top_level.txt
ax_lang-0.15.0.dist-info/RECORD
