Metadata-Version: 2.4
Name: ax-lang
Version: 0.15.0
Summary: axreldable programing language
Author-email: Aleksei Starikov <aleksei.starikov.ax@gmail.com>
License: MIT License
Project-URL: Repository, https://github.com/axreldable/ax-lang
Project-URL: Issues, https://github.com/axreldable/ax-lang/issues
Classifier: Development Status :: 3 - Alpha
Classifier: Intended Audience :: Developers
Classifier: Programming Language :: Python :: 3
Classifier: Programming Language :: Python :: 3.12
Requires-Python: >=3.12
Requires-Dist: antlr4-tools
Requires-Dist: antlr4-python3-runtime
Requires-Dist: click
Provides-Extra: test
Requires-Dist: pytest; extra == "test"
Requires-Dist: pytest-cov; extra == "test"
Requires-Dist: coverage; extra == "test"
Provides-Extra: doc
Requires-Dist: mkdocs; extra == "doc"
Requires-Dist: mkdocstrings; extra == "doc"
Requires-Dist: mkdocstrings[python]; extra == "doc"
Requires-Dist: mkdocs-material; extra == "doc"
Requires-Dist: Pygments; extra == "doc"
Requires-Dist: mike; extra == "doc"
Provides-Extra: dev
Requires-Dist: black; extra == "dev"
Requires-Dist: isort; extra == "dev"
Requires-Dist: flake8; extra == "dev"
Requires-Dist: pre-commit; extra == "dev"
Requires-Dist: ruff; extra == "dev"
Requires-Dist: twine; extra == "dev"
Requires-Dist: build; extra == "dev"
Provides-Extra: all
Requires-Dist: ax-lang[dev,doc,test]; extra == "all"
